scDREAMER/__init__.py
scDREAMER/model.py
scDREAMER/utils.py
scDREAMER/scDREAMER/__init__.py
scDREAMER/scDREAMER/model.py
scDREAMER/scDREAMER/utils.py
scDREAMER/scDREAMER_SUP/__init__.py
scDREAMER/scDREAMER_SUP/model.py
scDREAMER/scDREAMER_SUP/utils.py
scdreamer-0.0.0.dist-info/METADATA
scdreamer-0.0.0.dist-info/WHEEL
scdreamer-0.0.0.dist-info/licenses/LICENSE
scdreamer-0.0.0.dist-info/RECORD
