Metadata-Version: 2.1
Name: scDREAMER
Version: 0.0.0
Summary: scDREAMER is a single-cell data integration framework that employs a novel adversarial variational autoencoder for learning lower-dimensional cellular embeddings and a batch classifier neural network for the removal of batch effects.
Project-URL: DOI, https://doi.org/10.1038/s41467-023-43590-8
Project-URL: Homepage, https://github.com/Zafar-Lab/scDREAMER
Project-URL: Issues, https://github.com/Zafar-Lab/scDREAMER/issues
Author-email: Ajita Shree <ajitashree@cse.iitk.ac.in>, Musale Krushna Pavan <krushna@cse.iitk.ac.in>, Hamim Zafar <hamim@cse.iitk.ac.in>
License-File: LICENSE
Classifier: License :: OSI Approved :: MIT License
Classifier: Operating System :: OS Independent
Classifier: Programming Language :: Python :: 3
Requires-Python: >=3.7
Requires-Dist: scanpy
Requires-Dist: scikit-learn
Requires-Dist: scipy
Requires-Dist: tensorflow
